MANIFEST.in
setup.cfg
setup.py
PyBarCodeScan.egg-info/PKG-INFO
PyBarCodeScan.egg-info/SOURCES.txt
PyBarCodeScan.egg-info/dependency_links.txt
PyBarCodeScan.egg-info/requires.txt
PyBarCodeScan.egg-info/top_level.txt
PyBarCodeScan.egg-info/zip-safe
barcodescan/BarcodeReader.py
barcodescan/Config.py
barcodescan/Push_client.py
barcodescan/ScannedDataService.py
barcodescan/WorkerDao.py
barcodescan/__init__.py
barcodescan/barcodescanner_reader.py
barcodescan/barcodescanner_reader.service
barcodescan/barcodescanner_server.py
barcodescan/barcodescanner_server.service
barcodescan/templates/index.html
scripts/barcodescanner_reader
scripts/barcodescanner_server