Metadata-Version: 1.1
Name: PyBarCodeScan
Version: 0.1.66
Summary: Scan tool
Home-page: https://github.com/cfranke/scan
Author: Christian Franke
Author-email: chriss@frankeonline.net
License: APACHE LICENSE, VERSION 2.0
Platform: UNKNOWN
Classifier: Development Status :: 3 - Alpha
Classifier: Programming Language :: Python
